ddqa/__init__.py
ddqa/__main__.py
ddqa/_version.py
ddqa/py.typed
ddqa/app/__init__.py
ddqa/app/core.py
ddqa/app/style.py
ddqa/cache/__init__.py
ddqa/cache/github.py
ddqa/cache/jira.py
ddqa/cli/__init__.py
ddqa/cli/cache/__init__.py
ddqa/cli/cache/explore.py
ddqa/cli/cache/find.py
ddqa/cli/cache/purge.py
ddqa/cli/config/__init__.py
ddqa/cli/config/edit.py
ddqa/cli/config/explore.py
ddqa/cli/config/find.py
ddqa/cli/config/restore.py
ddqa/cli/config/set.py
ddqa/cli/config/show.py
ddqa/cli/create/__init__.py
ddqa/cli/status/__init__.py
ddqa/cli/sync/__init__.py
ddqa/config/__init__.py
ddqa/config/constants.py
ddqa/config/core.py
ddqa/config/file.py
ddqa/config/utils.py
ddqa/data/__init__.py
ddqa/data/logo.png
ddqa/data/shame.png
ddqa/models/__init__.py
ddqa/models/github.py
ddqa/models/jira.py
ddqa/models/config/__init__.py
ddqa/models/config/app.py
ddqa/models/config/auth.py
ddqa/models/config/repo.py
ddqa/models/config/team.py
ddqa/screens/__init__.py
ddqa/screens/configure.py
ddqa/screens/create.py
ddqa/screens/status.py
ddqa/screens/sync.py
ddqa/utils/__init__.py
ddqa/utils/ci.py
ddqa/utils/errors.py
ddqa/utils/fs.py
ddqa/utils/git.py
ddqa/utils/github.py
ddqa/utils/jira.py
ddqa/utils/network.py
ddqa/utils/structures.py
ddqa/utils/time.py
ddqa/utils/widgets.py
ddqa/widgets/__init__.py
ddqa/widgets/input.py
ddqa/widgets/layout.py
ddqa/widgets/static.py
ddqa-0.5.0.dist-info/METADATA
ddqa-0.5.0.dist-info/WHEEL
ddqa-0.5.0.dist-info/entry_points.txt
ddqa-0.5.0.dist-info/licenses/LICENSE-3rdparty.csv
ddqa-0.5.0.dist-info/licenses/LICENSE.txt
ddqa-0.5.0.dist-info/licenses/NOTICE
ddqa-0.5.0.dist-info/RECORD
