Metadata-Version: 2.3
Name: ddqa
Version: 0.5.0
Summary: Datadog's QA manager for releases of GitHub repositories
Project-URL: Source, https://github.com/DataDog/ddqa
Author-email: "Datadog, Inc." <dev@datadoghq.com>
License-Expression: MIT
License-File: LICENSE-3rdparty.csv
License-File: LICENSE.txt
License-File: NOTICE
Keywords: datadog,qa,testing,tooling
Classifier: Development Status :: 4 - Beta
Classifier: Intended Audience :: Developers
Classifier: Intended Audience :: System Administrators
Classifier: Programming Language :: Python :: 3.11
Classifier: Programming Language :: Python :: Implementation :: CPython
Requires-Python: >=3.11
Requires-Dist: click==8.1.7
Requires-Dist: httpx==0.25.2
Requires-Dist: pillow==10.1.0
Requires-Dist: platformdirs==4.0.0
Requires-Dist: pydantic-settings==2.3.0
Requires-Dist: pydantic==2.7.3
Requires-Dist: rich==13.7.0
Requires-Dist: textual==0.45.1
Requires-Dist: tomli-w==1.0.0
